czechfabric_sdk/__init__.py
czechfabric_sdk/cache.py
czechfabric_sdk/client.py
czechfabric_sdk/exceptions.py
czechfabric_sdk/logging_config.py
czechfabric_sdk/models.py
czechfabric_sdk-0.2.9.dist-info/licenses/LICENSE
czechfabric_sdk-0.2.9.dist-info/METADATA
czechfabric_sdk-0.2.9.dist-info/WHEEL
czechfabric_sdk-0.2.9.dist-info/top_level.txt
czechfabric_sdk-0.2.9.dist-info/RECORD
