Metadata-Version: 2.4
Name: czechfabric-sdk
Version: 0.2.9
Summary: Python SDK for Czech Intelligence Fabric (CzechFabric MCP)
Author-email: Abdulbasit Aliyu <ayindealiyu1@gmail.com>
License: MIT
Project-URL: Homepage, https://github.com/czechfabric/czechfabric-sdk
Project-URL: Repository, https://github.com/czechfabric/czechfabric-sdk
Project-URL: Issues, https://github.com/czechfabric/czechfabric-sdk/issues
Requires-Python: >=3.9
License-File: LICENSE
Requires-Dist: fastmcp>=2.0.0
Requires-Dist: pydantic>=2.0
Requires-Dist: async-lru>=2.0
Requires-Dist: httpx>=0.27.0
Dynamic: license-file
